Kuchizu
