Metadata-Version: 2.1
Name: Kuchizu
Version: 1.0.2
Summary: Kuchizu api.
Home-page: https://github.com/eternnoir/pyTelegramBotAPI
Author: Kuchizu
Author-email: Kuchizu@bk.ru
License: GPL2
Keywords: Kuchizu
Platform: UNKNOWN
Classifier: Development Status :: 5 - Production/Stable
Classifier: Programming Language :: Python :: 3
Classifier: Environment :: Console
Classifier: License :: OSI Approved :: GNU General Public License v2 (GPLv2)
